emport/__init__.py
emport/__version__.py
emport-1.4.1.dist-info/METADATA
emport-1.4.1.dist-info/WHEEL
emport-1.4.1.dist-info/licenses/LICENSE
emport-1.4.1.dist-info/RECORD
