Metadata-Version: 2.3
Name: emport
Version: 1.4.1
Summary: Utility library for performing programmatic imports
Project-URL: GitHub, https://github.com/vmalloc/emport
Author-email: Rotem Yaari <vmalloc@gmail.com>
License: BSD 3-Clause License
License-File: LICENSE
Classifier: Programming Language :: Python :: 3.8
Classifier: Programming Language :: Python :: 3.9
Classifier: Programming Language :: Python :: 3.10
Classifier: Programming Language :: Python :: 3.11
Classifier: Programming Language :: Python :: 3.12
Classifier: Programming Language :: Python :: 3.13
Requires-Python: >=3.8
Requires-Dist: logbook>=0.11.0
Provides-Extra: testing
Requires-Dist: dessert>=1.5.0; extra == 'testing'
Requires-Dist: pytest; extra == 'testing'
